MANIFEST.in
README.md
setup.py
deps/pybind11/.appveyor.yml
deps/pybind11/.git
deps/pybind11/.gitignore
deps/pybind11/.gitmodules
deps/pybind11/.readthedocs.yml
deps/pybind11/.travis.yml
deps/pybind11/CMakeLists.txt
deps/pybind11/CONTRIBUTING.md
deps/pybind11/ISSUE_TEMPLATE.md
deps/pybind11/LICENSE
deps/pybind11/MANIFEST.in
deps/pybind11/README.md
deps/pybind11/setup.cfg
deps/pybind11/setup.py
deps/pybind11/docs/Doxyfile
deps/pybind11/docs/Makefile
deps/pybind11/docs/basics.rst
deps/pybind11/docs/benchmark.py
deps/pybind11/docs/benchmark.rst
deps/pybind11/docs/changelog.rst
deps/pybind11/docs/classes.rst
deps/pybind11/docs/compiling.rst
deps/pybind11/docs/conf.py
deps/pybind11/docs/faq.rst
deps/pybind11/docs/index.rst
deps/pybind11/docs/intro.rst
deps/pybind11/docs/limitations.rst
deps/pybind11/docs/pybind11-logo.png
deps/pybind11/docs/pybind11_vs_boost_python1.png
deps/pybind11/docs/pybind11_vs_boost_python1.svg
deps/pybind11/docs/pybind11_vs_boost_python2.png
deps/pybind11/docs/pybind11_vs_boost_python2.svg
deps/pybind11/docs/reference.rst
deps/pybind11/docs/release.rst
deps/pybind11/docs/requirements.txt
deps/pybind11/docs/upgrade.rst
deps/pybind11/docs/_static/theme_overrides.css
deps/pybind11/docs/advanced/classes.rst
deps/pybind11/docs/advanced/embedding.rst
deps/pybind11/docs/advanced/exceptions.rst
deps/pybind11/docs/advanced/functions.rst
deps/pybind11/docs/advanced/misc.rst
deps/pybind11/docs/advanced/smart_ptrs.rst
deps/pybind11/docs/advanced/cast/chrono.rst
deps/pybind11/docs/advanced/cast/custom.rst
deps/pybind11/docs/advanced/cast/eigen.rst
deps/pybind11/docs/advanced/cast/functional.rst
deps/pybind11/docs/advanced/cast/index.rst
deps/pybind11/docs/advanced/cast/overview.rst
deps/pybind11/docs/advanced/cast/stl.rst
deps/pybind11/docs/advanced/cast/strings.rst
deps/pybind11/docs/advanced/pycpp/index.rst
deps/pybind11/docs/advanced/pycpp/numpy.rst
deps/pybind11/docs/advanced/pycpp/object.rst
deps/pybind11/docs/advanced/pycpp/utilities.rst
sparse_rrt.egg-info/PKG-INFO
sparse_rrt.egg-info/SOURCES.txt
sparse_rrt.egg-info/dependency_links.txt
sparse_rrt.egg-info/requires.txt
sparse_rrt.egg-info/top_level.txt
