Metadata-Version: 1.1
Name: sparse-rrt
Version: 0.0.2
Summary: Sparse stable trees planner
Home-page: https://github.com/olegsinyavskiy/sparse_rrt
Author: Oleg Sinyavskiy
Author-email: olegsinyavskiy@gmail.com
License: BSD License 2.0
Platform: UNKNOWN
Classifier: Development Status :: 3 - Alpha
Classifier: Intended Audience :: Developers
Classifier: Intended Audience :: Education
Classifier: Intended Audience :: Science/Research
Classifier: License :: OSI Approved :: BSD License
Classifier: Programming Language :: Python :: 2
Classifier: Programming Language :: Python :: 2.7
Classifier: Programming Language :: Python :: 3
Classifier: Programming Language :: Python :: 3.6
Classifier: Topic :: Software Development :: Libraries
Classifier: Topic :: Software Development :: Libraries :: Python Modules
